hackathon_18_demo/__init__.py
hackathon_18_demo/main.py
hackathon_18_demo-1.0.dist-info/AUTHORS
hackathon_18_demo-1.0.dist-info/LICENSE
hackathon_18_demo-1.0.dist-info/METADATA
hackathon_18_demo-1.0.dist-info/WHEEL
hackathon_18_demo-1.0.dist-info/RECORD
