Metadata-Version: 2.3
Name: hackathon-18-demo
Version: 1.0
Summary: A demo library for the hackathon
License: BSD-3-Clause
Author: Hugues de Laroussilhe
Author-email: hugues.delaroussilhe@meteoswiss.ch
Requires-Python: >=3.10,<3.13
Classifier: License :: OSI Approved :: BSD License
Classifier: Programming Language :: Python :: 3
Classifier: Programming Language :: Python :: 3.10
Classifier: Programming Language :: Python :: 3.11
Classifier: Programming Language :: Python :: 3.12
